subbot/__init__.py
subbot/__main__.py
subbot/lib/__init__.py
subbot/lib/config.py
subbot/lib/main_functions.py
subbot/lib/mkv.py
subbot/lib/stdout.py
subbot/lib/upload.py
subbot/utils/__init__.py
subbot/utils/dictionaries.py
subbot/utils/jsonutils.py
subbot/utils/misc.py
subbot-0.1.9.dist-info/LICENSE
subbot-0.1.9.dist-info/METADATA
subbot-0.1.9.dist-info/WHEEL
subbot-0.1.9.dist-info/entry_points.txt
subbot-0.1.9.dist-info/top_level.txt
subbot-0.1.9.dist-info/RECORD
