Metadata-Version: 2.1
Name: subbot
Version: 0.1.9
Summary: Automating subtitles management for lazy subbers.
Home-page: https://www.gitlab.com/Rubo/subbot
Author: Marco Rubin
Author-email: marco.rubin@protonmail.com
License: UNKNOWN
Keywords: subtitles,mkv,ass
Platform: UNKNOWN
Classifier: Development Status :: 3 - Alpha
Classifier: Environment :: Console
Classifier: License :: OSI Approved :: MIT License
Classifier: Operating System :: OS Independent
Classifier: Programming Language :: Python :: 3.8
Classifier: Topic :: Utilities
Requires-Python: >=3.8, <4
Requires-Dist: google-api-python-client (>=1.12.5)
Requires-Dist: google-auth-httplib2 (>=0.0.4)
Requires-Dist: google-auth-oauthlib (>=0.4.2)
Requires-Dist: mega.py (>=1.0.8)
Requires-Dist: PyInquirer-fork (==1.0.4)
Requires-Dist: pymkv (>=1.0.8)
Requires-Dist: rich (>=9.1.0)
